README.rst
setup.cfg
setup.py
tilecontrol/__init__.py
tilecontrol/cli.py
tilecontrol/compat.py
tilecontrol.egg-info/PKG-INFO
tilecontrol.egg-info/SOURCES.txt
tilecontrol.egg-info/dependency_links.txt
tilecontrol.egg-info/entry_points.txt
tilecontrol.egg-info/not-zip-safe
tilecontrol.egg-info/requires.txt
tilecontrol.egg-info/top_level.txt
tilecontrol/scripts/__init__.py
tilecontrol/scripts/checker.py
tilecontrol/scripts/checker_parser.py
tilecontrol/scripts/edgelist.py
tilecontrol/scripts/parser.py
tilecontrol/scripts/pxmfile.py