Metadata-Version: 1.0
Name: tilecontrol
Version: 0.1.6
Summary: PXM ingest quality control
Home-page: https://github.com/mapbox/tilecontrol
Author: Siyu Song
Author-email: siyu@mapbox.com
License: MIT
Platform: UNKNOWN
